smoothglue/__init__.py
smoothglue/django_mongo_adapter/__init__.py
smoothglue/django_mongo_adapter/apps.py
smoothglue/django_mongo_adapter/models.py
smoothglue/django_mongo_adapter/test_runner.py
smoothglue/django_mongo_adapter/utils.py
smoothglue_django_mongo_adapter-0.0.2.dist-info/LICENSE
smoothglue_django_mongo_adapter-0.0.2.dist-info/METADATA
smoothglue_django_mongo_adapter-0.0.2.dist-info/NOTICE
smoothglue_django_mongo_adapter-0.0.2.dist-info/WHEEL
smoothglue_django_mongo_adapter-0.0.2.dist-info/RECORD
