Metadata-Version: 2.3
Name: smoothglue_django_mongo_adapter
Version: 0.0.2
Summary: A Django adapter to facilitate using MongoDB with MongoEngine.
License: Proprietary
Author: BrainGu
Author-email: smoothglue@braingu.com
Requires-Python: >=3.10,<4.0
Classifier: Programming Language :: Python :: 3
Classifier: Framework :: Django
Classifier: Operating System :: OS Independent
Classifier: Intended Audience :: Developers
Classifier: Topic :: Software Development :: Libraries :: Python Modules
Requires-Dist: django (>=4.2)
Requires-Dist: mongoengine (>=0.29.1)
Requires-Dist: mongomock (>=4.3.0)
Requires-Dist: pymongo (>=4.15.3)
Project-URL: Homepage, https://braingu.com/solutions/smoothglue/
